Metadata-Version: 2.1
Name: rockettp3
Version: 1.0.0
Summary: An awesome package that does something
Home-page: http://pypi.python.org/pypi/rockettp3/
Author: omariabdessalam
Author-email: omariabdessalam18@gmail.com
License: LICENSE.txt
License-File: LICENSE.txt
Requires-Dist: rockettp3
